[
    {
        "title": "Andor",
        "tvdb_id": 393189,
        "poster_url": "https://image.tmdb.org/t/p/w500/khZqmwHQicTYoS7Flreb9EddFZC.jpg"
    },
    {
        "title": "Dept. Q",
        "tvdb_id": 445802,
        "poster_url": "https://image.tmdb.org/t/p/w500/h60alybJNgGGfPUbGGUXMXOoFvB.jpg"
    },
    {
        "title": "The Four Seasons",
        "tvdb_id": 444528,
        "poster_url": "https://image.tmdb.org/t/p/w500/w09XeYl096pwES8riRMZwEA9rnh.jpg"
    },
    {
        "title": "The Rehearsal",
        "tvdb_id": 405593,
        "poster_url": "https://image.tmdb.org/t/p/w500/mIevNYxovnH4sR22qkUmAgS5vdv.jpg"
    },
    {
        "title": "Tires",
        "tvdb_id": 446718,
        "poster_url": "https://image.tmdb.org/t/p/w500/cNHTFUV39qyEsm7edSaJdSqJYtJ.jpg"
    },
    {
        "title": "When Life Gives You Tangerines",
        "tvdb_id": 428338,
        "poster_url": "https://image.tmdb.org/t/p/w500/q29q6AByug53pnylCytwLA7m6AY.jpg"
    }
]
